Metadata-Version: 2.1
Name: cloudwatch-logs-insights-url-encoder
Version: 0.1.0
Summary: Simple module to generate cloudwatch logs insights URL
Home-page: https://github.com/sin9270/cloudwatch-logs-insights-url-encoder
Download-URL: https://github.com/sin9270/cloudwatch-logs-insights-url-encoder/archive/refs/tags/0.1.0.tar.gz
Author: WATANABE Shin
Author-email: sin9270@gmail.com
License: MIT
Platform: UNKNOWN
Classifier: Development Status :: 5 - Production/Stable
Classifier: Intended Audience :: Developers
Classifier: Topic :: Software Development :: Build Tools
Classifier: License :: OSI Approved :: MIT License
Classifier: Programming Language :: Python :: 3.7
Classifier: Programming Language :: Python :: 3.8
Classifier: Programming Language :: Python :: 3.9
License-File: LICENSE.txt
